echelon.py
Echelon8_test-0.0.1.dist-info/METADATA
Echelon8_test-0.0.1.dist-info/RECORD
Echelon8_test-0.0.1.dist-info/WHEEL
Echelon8_test-0.0.1.dist-info/top_level.txt
